austrian/__init__.py
austrian/designator.py
austrian/patterns.py
austrian/patterns_data.csv
austrian-0.2.1.dist-info/METADATA
austrian-0.2.1.dist-info/WHEEL
austrian-0.2.1.dist-info/RECORD
