Metadata-Version: 2.3
Name: austrian
Version: 0.2.1
Summary: A library to convert name of object into sidc code
Author: Serhii Syrota
Author-email: ssyrota241@gmail.com
Requires-Python: >=3.11
Classifier: Programming Language :: Python :: 3
Classifier: Programming Language :: Python :: 3.11
Classifier: Programming Language :: Python :: 3.12
Classifier: Programming Language :: Python :: 3.13
Requires-Dist: regex (==2023.10.3)
Requires-Dist: setuptools (==70.2.0)
Project-URL: Repository, https://github.com/NorwayPoppy/austrian_python
